Workbook

Sheet Sales
A1: Order no. | B1: Date | C1: Region | D1: Salesperson | E1: Category | F1: Unit Sold | G1: Unit Price | H1: Status | I1: Month | J1: Revenue After Returns | K1: Product | L1: Total Sales | M1: Month Number
A2: ORD-1 | B2: 11/30/2024 | C2: East | D2: Drusie Stedmond | E2: =IF(OR(K2="iPhone 15",K2="Samsung Galaxy"),"Mobiles",IF(OR(K2="HP Laptop",K2="Dell Laptop"),"Laptops","Accessories")) -> Accessories | F2: 14 | G2: 8148 | H2: Returned | I2: =TEXT(DATE(MID(B2,7,4),LEFT(B2,2),MID(B2,4,2)),"MMM") -> Nov | J2: =if(H2="Returned",0,L2) -> 0 | K2: Logitech Mouse | L2: 114072 | M2: =MONTH(DATE(MID(B2,7,4),LEFT(B2,2),MID(B2,4,2))) -> 11
A3: ORD-2 | B3: 07/29/2024 | C3: West | D3: Piggy Charlewood | E3: =IF(OR(K3="iPhone 15",K3="Samsung Galaxy"),"Mobiles",IF(OR(K3="HP Laptop",K3="Dell Laptop"),"Laptops","Accessories")) -> Accessories | F3: 3 | G3: 74394 | H3: Pending | I3: =TEXT(DATE(MID(B3,7,4),LEFT(B3,2),MID(B3,4,2)),"MMM") -> Jul | J3: =if(H3="Returned",0,L3) -> 223182 | K3: Boat Earbuds | L3: 223182 | M3: =MONTH(DATE(MID(B3,7,4),LEFT(B3,2),MID(B3,4,2))) -> 7
A4: ORD-3 | B4: 04/14/2024 | C4: South | D4: Duky Ronisch | E4: =IF(OR(K4="iPhone 15",K4="Samsung Galaxy"),"Mobiles",IF(OR(K4="HP Laptop",K4="Dell Laptop"),"Laptops","Accessories")) -> Mobiles | F4: 19 | G4: 59294 | H4: Completed | I4: =TEXT(DATE(MID(B4,7,4),LEFT(B4,2),MID(B4,4,2)),"MMM") -> Apr | J4: =if(H4="Returned",0,L4) -> 1126586 | K4: iPhone 15 | L4: 1126586 | M4: =MONTH(DATE(MID(B4,7,4),LEFT(B4,2),MID(B4,4,2))) -> 4
A5: ORD-4 | B5: 45507 | C5: West | D5: Gabe Howell | E5: =IF(OR(K5="iPhone 15",K5="Samsung Galaxy"),"Mobiles",IF(OR(K5="HP Laptop",K5="Dell Laptop"),"Laptops","Accessories")) -> Laptops | F5: 1 | G5: 63918 | H5: Pending | I5: =TEXT(DATE(MID(B5,7,4),LEFT(B5,2),MID(B5,4,2)),"MMM") -> Mar | J5: =if(H5="Returned",0,L5) -> 63918 | K5: HP Laptop | L5: 63918 | M5: =MONTH(DATE(MID(B5,7,4),LEFT(B5,2),MID(B5,4,2))) -> 3
A6: ORD-5 | B6: 07/31/2024 | C6: East | D6: Burr Jago | E6: =IF(OR(K6="iPhone 15",K6="Samsung Galaxy"),"Mobiles",IF(OR(K6="HP Laptop",K6="Dell Laptop"),"Laptops","Accessories")) -> Accessories | F6: 1 | G6: 75554 | H6: Returned | I6: =TEXT(DATE(MID(B6,7,4),LEFT(B6,2),MID(B6,4,2)),"MMM") -> Jul | J6: =if(H6="Returned",0,L6) -> 0 | K6: Boat Earbuds | L6: 75554 | M6: =MONTH(DATE(MID(B6,7,4),LEFT(B6,2),MID(B6,4,2))) -> 7
A7: ORD-6 | B7: 45629 | C7: South | D7: Wenonah Hallatt | E7: =IF(OR(K7="iPhone 15",K7="Samsung Galaxy"),"Mobiles",IF(OR(K7="HP Laptop",K7="Dell Laptop"),"Laptops","Accessories")) -> Laptops | F7: 3 | G7: 31893 | H7: Pending | I7: =TEXT(DATE(MID(B7,7,4),LEFT(B7,2),MID(B7,4,2)),"MMM") -> Mar | J7: =if(H7="Returned",0,L7) -> 95679 | K7: Dell Laptop | L7: 95679 | M7: =MONTH(DATE(MID(B7,7,4),LEFT(B7,2),MID(B7,4,2))) -> 3
A8: ORD-7 | B8: 10/22/2024 | C8: West | D8: Lurette Heavyside | E8: =IF(OR(K8="iPhone 15",K8="Samsung Galaxy"),"Mobiles",IF(OR(K8="HP Laptop",K8="Dell Laptop"),"Laptops","Accessories")) -> Laptops | F8: 16 | G8: 78420 | H8: Completed | I8: =TEXT(DATE(MID(B8,7,4),LEFT(B8,2),MID(B8,4,2)),"MMM") -> Oct | J8: =if(H8="Returned",0,L8) -> 1254720 | K8: Dell Laptop | L8: 1254720 | M8: =MONTH(DATE(MID(B8,7,4),LEFT(B8,2),MID(B8,4,2))) -> 10
A9: ORD-8 | B9: 06/16/2024 | C9: East | D9: Malcolm Poulsum | E9: =IF(OR(K9="iPhone 15",K9="Samsung Galaxy"),"Mobiles",IF(OR(K9="HP Laptop",K9="Dell Laptop"),"Laptops","Accessories")) -> Laptops | F9: 6 | G9: 56487 | H9: Completed | I9: =TEXT(DATE(MID(B9,7,4),LEFT(B9,2),MID(B9,4,2)),"MMM") -> Jun | J9: =if(H9="Returned",0,L9) -> 338922 | K9: Dell Laptop | L9: 338922 | M9: =MONTH(DATE(MID(B9,7,4),LEFT(B9,2),MID(B9,4,2))) -> 6
A10: ORD-9 | B10: 02/15/2024 | C10: East | D10: Carr Prisley | E10: =IF(OR(K10="iPhone 15",K10="Samsung Galaxy"),"Mobiles",IF(OR(K10="HP Laptop",K10="Dell Laptop"),"Laptops","Accessories")) -> Mobiles | F10: 2 | G10: 12129 | H10: Returned | I10: =TEXT(DATE(MID(B10,7,4),LEFT(B10,2),MID(B10,4,2)),"MMM") -> Feb | J10: =if(H10="Returned",0,L10) -> 0 | K10: Samsung Galaxy | L10: 24258 | M10: =MONTH(DATE(MID(B10,7,4),LEFT(B10,2),MID(B10,4,2))) -> 2
A11: ORD-10 | B11: 45447 | C11: East | D11: Chickie Dayley | E11: =IF(OR(K11="iPhone 15",K11="Samsung Galaxy"),"Mobiles",IF(OR(K11="HP Laptop",K11="Dell Laptop"),"Laptops","Accessories")) -> Accessories | F11: 18 | G11: 4204 | H11: Returned | I11: =TEXT(DATE(MID(B11,7,4),LEFT(B11,2),MID(B11,4,2)),"MMM") -> Apr | J11: =if(H11="Returned",0,L11) -> 0 | K11: OnePlus TV | L11: 75672 | M11: =MONTH(DATE(MID(B11,7,4),LEFT(B11,2),MID(B11,4,2))) -> 4
A12: ORD-11 | B12: 45352 | C12: North | D12: Annalise Plowman | E12: =IF(OR(K12="iPhone 15",K12="Samsung Galaxy"),"Mobiles",IF(OR(K12="HP Laptop",K12="Dell Laptop"),"Laptops","Accessories")) -> Accessories | F12: 13 | G12: 22388 | H12: Pending | I12: =TEXT(DATE(MID(B12,7,4),LEFT(B12,2),MID(B12,4,2)),"MMM") -> Jan | J12: =if(H12="Returned",0,L12) -> 291044 | K12: Logitech Mouse | L12: 291044 | M12: =MONTH(DATE(MID(B12,7,4),LEFT(B12,2),MID(B12,4,2))) -> 1
A13: ORD-12 | B13: 09/21/2024 | C13: North | D13: Janessa Bladder | E13: =IF(OR(K13="iPhone 15",K13="Samsung Galaxy"),"Mobiles",IF(OR(K13="HP Laptop",K13="Dell Laptop"),"Laptops","Accessories")) -> Mobiles | F13: 14 | G13: 71188 | H13: Returned | I13: =TEXT(DATE(MID(B13,7,4),LEFT(B13,2),MID(B13,4,2)),"MMM") -> Sep | J13: =if(H13="Returned",0,L13) -> 0 | K13: iPhone 15 | L13: 996632 | M13: =MONTH(DATE(MID(B13,7,4),LEFT(B13,2),MID(B13,4,2))) -> 9
A14: ORD-13 | B14: 45297 | C14: South | D14: Orrin Suarez | E14: =IF(OR(K14="iPhone 15",K14="Samsung Galaxy"),"Mobiles",IF(OR(K14="HP Laptop",K14="Dell Laptop"),"Laptops","Accessories")) -> Laptops | F14: 16 | G14: 10359 | H14: Completed | I14: =TEXT(DATE(MID(B14,7,4),LEFT(B14,2),MID(B14,4,2)),"MMM") -> Jun | J14: =if(H14="Returned",0,L14) -> 165744 | K14: HP Laptop | L14: 165744 | M14: =MONTH(DATE(MID(B14,7,4),LEFT(B14,2),MID(B14,4,2))) -> 6
A15: ORD-14 | B15: 12/15/2024 | C15: East | D15: Fallon Simonassi | E15: =IF(OR(K15="iPhone 15",K15="Samsung Galaxy"),"Mobiles",IF(OR(K15="HP Laptop",K15="Dell Laptop"),"Laptops","Accessories")) -> Mobiles | F15: 13 | G15: 21620 | H15: Pending | I15: =TEXT(DATE(MID(B15,7,4),LEFT(B15,2),MID(B15,4,2)),"MMM") -> Dec | J15: =if(H15="Returned",0,L15) -> 281060 | K15: Samsung Galaxy | L15: 281060 | M15: =MONTH(DATE(MID(B15,7,4),LEFT(B15,2),MID(B15,4,2))) -> 12
A16: ORD-15 | B16: 11/20/2024 | C16: North | D16: Bobinette Lakenton | E16: =IF(OR(K16="iPhone 15",K16="Samsung Galaxy"),"Mobiles",IF(OR(K16="HP Laptop",K16="Dell Laptop"),"Laptops","Accessories")) -> Accessories | F16: 5 | G16: 45721 | H16: Returned | I16: =TEXT(DATE(MID(B16,7,4),LEFT(B16,2),MID(B16,4,2)),"MMM") -> Nov | J16: =if(H16="Returned",0,L16) -> 0 | K16: OnePlus TV | L16: 228605 | M16: =MONTH(DATE(MID(B16,7,4),LEFT(B16,2),MID(B16,4,2))) -> 11
A17: ORD-16 | B17: 45602 | C17: North | D17: Elisabeth Give | E17: =IF(OR(K17="iPhone 15",K17="Samsung Galaxy"),"Mobiles",IF(OR(K17="HP Laptop",K17="Dell Laptop"),"Laptops","Accessories")) -> Accessories | F17: 17 | G17: 19213 | H17: Pending | I17: =TEXT(DATE(MID(B17,7,4),LEFT(B17,2),MID(B17,4,2)),"MMM") -> Jun | J17: =if(H17="Returned",0,L17) -> 326621 | K17: OnePlus TV | L17: 326621 | M17: =MONTH(DATE(MID(B17,7,4),LEFT(B17,2),MID(B17,4,2))) -> 6
A18: ORD-17 | B18: 12/29/2024 | C18: East | D18: Meggi Bodechon | E18: =IF(OR(K18="iPhone 15",K18="Samsung Galaxy"),"Mobiles",IF(OR(K18="HP Laptop",K18="Dell Laptop"),"Laptops","Accessories")) -> Accessories | F18: 5 | G18: 16412 | H18: Pending | I18: =TEXT(DATE(MID(B18,7,4),LEFT(B18,2),MID(B18,4,2)),"MMM") -> Dec | J18: =if(H18="Returned",0,L18) -> 82060 | K18: Logitech Mouse | L18: 82060 | M18: =MONTH(DATE(MID(B18,7,4),LEFT(B18,2),MID(B18,4,2))) -> 12
A19: ORD-18 | B19: 01/14/2024 | C19: South | D19: Lorrie Rogers | E19: =IF(OR(K19="iPhone 15",K19="Samsung Galaxy"),"Mobiles",IF(OR(K19="HP Laptop",K19="Dell Laptop"),"Laptops","Accessories")) -> Laptops | F19: 19 | G19: 47133 | H19: Completed | I19: =TEXT(DATE(MID(B19,7,4),LEFT(B19,2),MID(B19,4,2)),"MMM") -> Jan | J19: =if(H19="Returned",0,L19) -> 895527 | K19: HP Laptop | L19: 895527 | M19: =MONTH(DATE(MID(B19,7,4),LEFT(B19,2),MID(B19,4,2))) -> 1
A20: ORD-19 | B20: 12/23/2024 | C20: North | D20: Avictor Curreen | E20: =IF(OR(K20="iPhone 15",K20="Samsung Galaxy"),"Mobiles",IF(OR(K20="HP Laptop",K20="Dell Laptop"),"Laptops","Accessories")) -> Accessories | F20: 6 | G20: 32588 | H20: Returned | I20: =TEXT(DATE(MID(B20,7,4),LEFT(B20,2),MID(B20,4,2)),"MMM") -> Dec | J20: =if(H20="Returned",0,L20) -> 0 | K20: Logitech Mouse | L20: 195528 | M20: =MONTH(DATE(MID(B20,7,4),LEFT(B20,2),MID(B20,4,2))) -> 12
A21: ORD-20 | B21: 04/26/2024 | C21: South | D21: Zilvia Muat | E21: =IF(OR(K21="iPhone 15",K21="Samsung Galaxy"),"Mobiles",IF(OR(K21="HP Laptop",K21="Dell Laptop"),"Laptops","Accessories")) -> Accessories | F21: 5 | G21: 22173 | H21: Pending | I21: =TEXT(DATE(MID(B21,7,4),LEFT(B21,2),MID(B21,4,2)),"MMM") -> Apr | J21: =if(H21="Returned",0,L21) -> 110865 | K21: Logitech Mouse | L21: 110865 | M21: =MONTH(DATE(MID(B21,7,4),LEFT(B21,2),MID(B21,4,2))) -> 4
A22: ORD-21 | B22: 10/24/2024 | C22: East | D22: Bradley Wiggins | E22: =IF(OR(K22="iPhone 15",K22="Samsung Galaxy"),"Mobiles",IF(OR(K22="HP Laptop",K22="Dell Laptop"),"Laptops","Accessories")) -> Laptops | F22: 16 | G22: 77212 | H22: Completed | I22: =TEXT(DATE(MID(B22,7,4),LEFT(B22,2),MID(B22,4,2)),"MMM") -> Oct | J22: =if(H22="Returned",0,L22) -> 1235392 | K22: Dell Laptop | L22: 1235392 | M22: =MONTH(DATE(MID(B22,7,4),LEFT(B22,2),MID(B22,4,2))) -> 10
A23: ORD-22 | B23: 09/18/2024 | C23: North | D23: Carey Oloshin | E23: =IF(OR(K23="iPhone 15",K23="Samsung Galaxy"),"Mobiles",IF(OR(K23="HP Laptop",K23="Dell Laptop"),"Laptops","Accessories")) -> Laptops | F23: 5 | G23: 78714 | H23: Returned | I23: =TEXT(DATE(MID(B23,7,4),LEFT(B23,2),MID(B23,4,2)),"MMM") -> Sep | J23: =if(H23="Returned",0,L23) -> 0 | K23: Dell Laptop | L23: 393570 | M23: =MONTH(DATE(MID(B23,7,4),LEFT(B23,2),MID(B23,4,2))) -> 9
A24: ORD-23 | B24: 03/29/2024 | C24: East | D24: Moreen Yeldham | E24: =IF(OR(K24="iPhone 15",K24="Samsung Galaxy"),"Mobiles",IF(OR(K24="HP Laptop",K24="Dell Laptop"),"Laptops","Accessories")) -> Laptops | F24: 2 | G24: 73168 | H24: Pending | I24: =TEXT(DATE(MID(B24,7,4),LEFT(B24,2),MID(B24,4,2)),"MMM") -> Mar | J24: =if(H24="Returned",0,L24) -> 146336 | K24: HP Laptop | L24: 146336 | M24: =MONTH(DATE(MID(B24,7,4),LEFT(B24,2),MID(B24,4,2))) -> 3
A25: ORD-24 | B25: 45512 | C25: South | D25: Trula Cobbin | E25: =IF(OR(K25="iPhone 15",K25="Samsung Galaxy"),"Mobiles",IF(OR(K25="HP Laptop",K25="Dell Laptop"),"Laptops","Accessories")) -> Laptops | F25: 8 | G25: 42894 | H25: Returned | I25: =TEXT(DATE(MID(B25,7,4),LEFT(B25,2),MID(B25,4,2)),"MMM") -> Aug | J25: =if(H25="Returned",0,L25) -> 0 | K25: Dell Laptop | L25: 343152 | M25: =MONTH(DATE(MID(B25,7,4),LEFT(B25,2),MID(B25,4,2))) -> 8
A26: ORD-25 | B26: 45355 | C26: South | D26: Lizette Hadye | E26: =IF(OR(K26="iPhone 15",K26="Samsung Galaxy"),"Mobiles",IF(OR(K26="HP Laptop",K26="Dell Laptop"),"Laptops","Accessories")) -> Accessories | F26: 5 | G26: 66731 | H26: Completed | I26: =TEXT(DATE(MID(B26,7,4),LEFT(B26,2),MID(B26,4,2)),"MMM") -> Apr | J26: =if(H26="Returned",0,L26) -> 333655 | K26: OnePlus TV | L26: 333655 | M26: =MONTH(DATE(MID(B26,7,4),LEFT(B26,2),MID(B26,4,2))) -> 4
A27: ORD-26 | B27: 03/23/2024 | C27: West | D27: Fey Walworth | E27: =IF(OR(K27="iPhone 15",K27="Samsung Galaxy"),"Mobiles",IF(OR(K27="HP Laptop",K27="Dell Laptop"),"Laptops","Accessories")) -> Accessories | F27: 4 | G27: 73151 | H27: Completed | I27: =TEXT(DATE(MID(B27,7,4),LEFT(B27,2),MID(B27,4,2)),"MMM") -> Mar | J27: =if(H27="Returned",0,L27) -> 292604 | K27: OnePlus TV | L27: 292604 | M27: =MONTH(DATE(MID(B27,7,4),LEFT(B27,2),MID(B27,4,2))) -> 3
A28: ORD-27 | B28: 45298 | C28: South | D28: Casper Tixall | E28: =IF(OR(K28="iPhone 15",K28="Samsung Galaxy"),"Mobiles",IF(OR(K28="HP Laptop",K28="Dell Laptop"),"Laptops","Accessories")) -> Accessories | F28: 10 | G28: 18040 | H28: Completed | I28: =TEXT(DATE(MID(B28,7,4),LEFT(B28,2),MID(B28,4,2)),"MMM") -> Jul | J28: =if(H28="Returned",0,L28) -> 180400 | K28: Boat Earbuds | L28: 180400 | M28: =MONTH(DATE(MID(B28,7,4),LEFT(B28,2),MID(B28,4,2))) -> 7
A29: ORD-28 | B29: 45323 | C29: East | D29: Chance Abbiss | E29: =IF(OR(K29="iPhone 15",K29="Samsung Galaxy"),"Mobiles",IF(OR(K29="HP Laptop",K29="Dell Laptop"),"Laptops","Accessories")) -> Accessories | F29: 8 | G29: 79316 | H29: Completed | I29: =TEXT(DATE(MID(B29,7,4),LEFT(B29,2),MID(B29,4,2)),"MMM") -> Jan | J29: =if(H29="Returned",0,L29) -> 634528 | K29: OnePlus TV | L29: 634528 | M29: =MONTH(DATE(MID(B29,7,4),LEFT(B29,2),MID(B29,4,2))) -> 1
A30: ORD-29 | B30: 01/27/2024 | C30: North | D30: Kelley Carren | E30: =IF(OR(K30="iPhone 15",K30="Samsung Galaxy"),"Mobiles",IF(OR(K30="HP Laptop",K30="Dell Laptop"),"Laptops","Accessories")) -> Mobiles | F30: 18 | G30: 27111 | H30: Pending | I30: =TEXT(DATE(MID(B30,7,4),LEFT(B30,2),MID(B30,4,2)),"MMM") -> Jan | J30: =if(H30="Returned",0,L30) -> 487998 | K30: iPhone 15 | L30: 487998 | M30: =MONTH(DATE(MID(B30,7,4),LEFT(B30,2),MID(B30,4,2))) -> 1
A31: ORD-30 | B31: 45424 | C31: West | D31: Royal Madner | E31: =IF(OR(K31="iPhone 15",K31="Samsung Galaxy"),"Mobiles",IF(OR(K31="HP Laptop",K31="Dell Laptop"),"Laptops","Accessories")) -> Mobiles | F31: 14 | G31: 55771 | H31: Pending | I31: =TEXT(DATE(MID(B31,7,4),LEFT(B31,2),MID(B31,4,2)),"MMM") -> Dec | J31: =if(H31="Returned",0,L31) -> 780794 | K31: iPhone 15 | L31: 780794 | M31: =MONTH(DATE(MID(B31,7,4),LEFT(B31,2),MID(B31,4,2))) -> 12
A32: ORD-31 | B32: 03/25/2024 | C32: East | D32: Christoper Maevela | E32: =IF(OR(K32="iPhone 15",K32="Samsung Galaxy"),"Mobiles",IF(OR(K32="HP Laptop",K32="Dell Laptop"),"Laptops","Accessories")) -> Accessories | F32: 6 | G32: 20955 | H32: Completed | I32: =TEXT(DATE(MID(B32,7,4),LEFT(B32,2),MID(B32,4,2)),"MMM") -> Mar | J32: =if(H32="Returned",0,L32) -> 125730 | K32: Logitech Mouse | L32: 125730 | M32: =MONTH(DATE(MID(B32,7,4),LEFT(B32,2),MID(B32,4,2))) -> 3
A33: ORD-32 | B33: 10/31/2024 | C33: West | D33: Torrie Targett | E33: =IF(OR(K33="iPhone 15",K33="Samsung Galaxy"),"Mobiles",IF(OR(K33="HP Laptop",K33="Dell Laptop"),"Laptops","Accessories")) -> Mobiles | F33: 9 | G33: 2998 | H33: Completed | I33: =TEXT(DATE(MID(B33,7,4),LEFT(B33,2),MID(B33,4,2)),"MMM") -> Oct | J33: =if(H33="Returned",0,L33) -> 26982 | K33: iPhone 15 | L33: 26982 | M33: =MONTH(DATE(MID(B33,7,4),LEFT(B33,2),MID(B33,4,2))) -> 10
A34: ORD-33 | B34: 45331 | C34: North | D34: Griffin Showl | E34: =IF(OR(K34="iPhone 15",K34="Samsung Galaxy"),"Mobiles",IF(OR(K34="HP Laptop",K34="Dell Laptop"),"Laptops","Accessories")) -> Mobiles | F34: 11 | G34: 65142 | H34: Pending | I34: =TEXT(DATE(MID(B34,7,4),LEFT(B34,2),MID(B34,4,2)),"MMM") -> Sep | J34: =if(H34="Returned",0,L34) -> 716562 | K34: Samsung Galaxy | L34: 716562 | M34: =MONTH(DATE(MID(B34,7,4),LEFT(B34,2),MID(B34,4,2))) -> 9
A35: ORD-34 | B35: 45601 | C35: South | D35: Eldredge Hair | E35: =IF(OR(K35="iPhone 15",K35="Samsung Galaxy"),"Mobiles",IF(OR(K35="HP Laptop",K35="Dell Laptop"),"Laptops","Accessories")) -> Accessories | F35: 17 | G35: 29927 | H35: Pending | I35: =TEXT(DATE(MID(B35,7,4),LEFT(B35,2),MID(B35,4,2)),"MMM") -> May | J35: =if(H35="Returned",0,L35) -> 508759 | K35: Logitech Mouse | L35: 508759 | M35: =MONTH(DATE(MID(B35,7,4),LEFT(B35,2),MID(B35,4,2))) -> 5
A36: ORD-35 | B36: 08/25/2024 | C36: West | D36: Gaspard Obbard | E36: =IF(OR(K36="iPhone 15",K36="Samsung Galaxy"),"Mobiles",IF(OR(K36="HP Laptop",K36="Dell Laptop"),"Laptops","Accessories")) -> Mobiles | F36: 9 | G36: 46394 | H36: Completed | I36: =TEXT(DATE(MID(B36,7,4),LEFT(B36,2),MID(B36,4,2)),"MMM") -> Aug | J36: =if(H36="Returned",0,L36) -> 417546 | K36: iPhone 15 | L36: 417546 | M36: =MONTH(DATE(MID(B36,7,4),LEFT(B36,2),MID(B36,4,2))) -> 8
A37: ORD-36 | B37: 45598 | C37: North | D37: Clari Pablo | E37: =IF(OR(K37="iPhone 15",K37="Samsung Galaxy"),"Mobiles",IF(OR(K37="HP Laptop",K37="Dell Laptop"),"Laptops","Accessories")) -> Mobiles | F37: 2 | G37: 39851 | H37: Pending | I37: =TEXT(DATE(MID(B37,7,4),LEFT(B37,2),MID(B37,4,2)),"MMM") -> Feb | J37: =if(H37="Returned",0,L37) -> 79702 | K37: iPhone 15 | L37: 79702 | M37: =MONTH(DATE(MID(B37,7,4),LEFT(B37,2),MID(B37,4,2))) -> 2
A38: ORD-37 | B38: 45602 | C38: West | D38: Bordy Morilla | E38: =IF(OR(K38="iPhone 15",K38="Samsung Galaxy"),"Mobiles",IF(OR(K38="HP Laptop",K38="Dell Laptop"),"Laptops","Accessories")) -> Mobiles | F38: 19 | G38: 16416 | H38: Returned | I38: =TEXT(DATE(MID(B38,7,4),LEFT(B38,2),MID(B38,4,2)),"MMM") -> Jun | J38: =if(H38="Returned",0,L38) -> 0 | K38: iPhone 15 | L38: 311904 | M38: =MONTH(DATE(MID(B38,7,4),LEFT(B38,2),MID(B38,4,2))) -> 6
A39: ORD-38 | B39: 04/29/2024 | C39: East | D39: Giustino Thorne | E39: =IF(OR(K39="iPhone 15",K39="Samsung Galaxy"),"Mobiles",IF(OR(K39="HP Laptop",K39="Dell Laptop"),"Laptops","Accessories")) -> Accessories | F39: 2 | G39: 34042 | H39: Pending | I39: =TEXT(DATE(MID(B39,7,4),LEFT(B39,2),MID(B39,4,2)),"MMM") -> Apr | J39: =if(H39="Returned",0,L39) -> 68084 | K39: OnePlus TV | L39: 68084 | M39: =MONTH(DATE(MID(B39,7,4),LEFT(B39,2),MID(B39,4,2))) -> 4
A40: ORD-39 | B40: 11/14/2024 | C40: West | D40: Winnifred Pocklington | E40: =IF(OR(K40="iPhone 15",K40="Samsung Galaxy"),"Mobiles",IF(OR(K40="HP Laptop",K40="Dell Laptop"),"Laptops","Accessories")) -> Mobiles | F40: 15 | G40: 53601 | H40: Returned | I40: =TEXT(DATE(MID(B40,7,4),LEFT(B40,2),MID(B40,4,2)),"MMM") -> Nov | J40: =if(H40="Returned",0,L40) -> 0 | K40: iPhone 15 | L40: 804015 | M40: =MONTH(DATE(MID(B40,7,4),LEFT(B40,2),MID(B40,4,2))) -> 11
A41: ORD-40 | B41: 08/13/2024 | C41: East | D41: Humfrid Brockman | E41: =IF(OR(K41="iPhone 15",K41="Samsung Galaxy"),"Mobiles",IF(OR(K41="HP Laptop",K41="Dell Laptop"),"Laptops","Accessories")) -> Mobiles | F41: 15 | G41: 51576 | H41: Returned | I41: =TEXT(DATE(MID(B41,7,4),LEFT(B41,2),MID(B41,4,2)),"MMM") -> Aug | J41: =if(H41="Returned",0,L41) -> 0 | K41: Samsung Galaxy | L41: 773640 | M41: =MONTH(DATE(MID(B41,7,4),LEFT(B41,2),MID(B41,4,2))) -> 8
A42: ORD-41 | B42: 45510 | C42: West | D42: Cosme Leonida | E42: =IF(OR(K42="iPhone 15",K42="Samsung Galaxy"),"Mobiles",IF(OR(K42="HP Laptop",K42="Dell Laptop"),"Laptops","Accessories")) -> Laptops | F42: 4 | G42: 55675 | H42: Pending | I42: =TEXT(DATE(MID(B42,7,4),LEFT(B42,2),MID(B42,4,2)),"MMM") -> Jun | J42: =if(H42="Returned",0,L42) -> 222700 | K42: HP Laptop | L42: 222700 | M42: =MONTH(DATE(MID(B42,7,4),LEFT(B42,2),MID(B42,4,2))) -> 6
A43: ORD-42 | B43: 45331 | C43: South | D43: Tomas Wybourne | E43: =IF(OR(K43="iPhone 15",K43="Samsung Galaxy"),"Mobiles",IF(OR(K43="HP Laptop",K43="Dell Laptop"),"Laptops","Accessories")) -> Mobiles | F43: 12 | G43: 66364 | H43: Returned | I43: =TEXT(DATE(MID(B43,7,4),LEFT(B43,2),MID(B43,4,2)),"MMM") -> Sep | J43: =if(H43="Returned",0,L43) -> 0 | K43: iPhone 15 | L43: 796368 | M43: =MONTH(DATE(MID(B43,7,4),LEFT(B43,2),MID(B43,4,2))) -> 9
A44: ORD-43 | B44: 01/31/2024 | C44: East | D44: Mufinella Liversley | E44: =IF(OR(K44="iPhone 15",K44="Samsung Galaxy"),"Mobiles",IF(OR(K44="HP Laptop",K44="Dell Laptop"),"Laptops","Accessories")) -> Mobiles | F44: 18 | G44: 4632 | H44: Pending | I44: =TEXT(DATE(MID(B44,7,4),LEFT(B44,2),MID(B44,4,2)),"MMM") -> Jan | J44: =if(H44="Returned",0,L44) -> 83376 | K44: Samsung Galaxy | L44: 83376 | M44: =MONTH(DATE(MID(B44,7,4),LEFT(B44,2),MID(B44,4,2))) -> 1
A45: ORD-44 | B45: 08/15/2024 | C45: East | D45: Emmett Coode | E45: =IF(OR(K45="iPhone 15",K45="Samsung Galaxy"),"Mobiles",IF(OR(K45="HP Laptop",K45="Dell Laptop"),"Laptops","Accessories")) -> Accessories | F45: 20 | G45: 74726 | H45: Pending | I45: =TEXT(DATE(MID(B45,7,4),LEFT(B45,2),MID(B45,4,2)),"MMM") -> Aug | J45: =if(H45="Returned",0,L45) -> 1494520 | K45: OnePlus TV | L45: 1494520 | M45: =MONTH(DATE(MID(B45,7,4),LEFT(B45,2),MID(B45,4,2))) -> 8
A46: ORD-45 | B46: 10/13/2024 | C46: South | D46: Koenraad Kryszka | E46: =IF(OR(K46="iPhone 15",K46="Samsung Galaxy"),"Mobiles",IF(OR(K46="HP Laptop",K46="Dell Laptop"),"Laptops","Accessories")) -> Mobiles | F46: 1 | G46: 1900 | H46: Pending | I46: =TEXT(DATE(MID(B46,7,4),LEFT(B46,2),MID(B46,4,2)),"MMM") -> Oct | J46: =if(H46="Returned",0,L46) -> 1900 | K46: iPhone 15 | L46: 1900 | M46: =MONTH(DATE(MID(B46,7,4),LEFT(B46,2),MID(B46,4,2))) -> 10
A47: ORD-46 | B47: 45330 | C47: East | D47: Jase Pallis | E47: =IF(OR(K47="iPhone 15",K47="Samsung Galaxy"),"Mobiles",IF(OR(K47="HP Laptop",K47="Dell Laptop"),"Laptops","Accessories")) -> Accessories | F47: 17 | G47: 34574 | H47: Returned | I47: =TEXT(DATE(MID(B47,7,4),LEFT(B47,2),MID(B47,4,2)),"MMM") -> Aug | J47: =if(H47="Returned",0,L47) -> 0 | K47: Logitech Mouse | L47: 587758 | M47: =MONTH(DATE(MID(B47,7,4),LEFT(B47,2),MID(B47,4,2))) -> 8
A48: ORD-47 | B48: 02/14/2024 | C48: West | D48: Ferris Corneille | E48: =IF(OR(K48="iPhone 15",K48="Samsung Galaxy"),"Mobiles",IF(OR(K48="HP Laptop",K48="Dell Laptop"),"Laptops","Accessories")) -> Mobiles | F48: 20 | G48: 59847 | H48: Completed | I48: =TEXT(DATE(MID(B48,7,4),LEFT(B48,2),MID(B48,4,2)),"MMM") -> Feb | J48: =if(H48="Returned",0,L48) -> 1196940 | K48: Samsung Galaxy | L48: 1196940 | M48: =MONTH(DATE(MID(B48,7,4),LEFT(B48,2),MID(B48,4,2))) -> 2
A49: ORD-48 | B49: 01/24/2024 | C49: South | D49: Sigfrid Leyre | E49: =IF(OR(K49="iPhone 15",K49="Samsung Galaxy"),"Mobiles",IF(OR(K49="HP Laptop",K49="Dell Laptop"),"Laptops","Accessories")) -> Accessories | F49: 10 | G49: 24649 | H49: Completed | I49: =TEXT(DATE(MID(B49,7,4),LEFT(B49,2),MID(B49,4,2)),"MMM") -> Jan | J49: =if(H49="Returned",0,L49) -> 246490 | K49: Boat Earbuds | L49: 246490 | M49: =MONTH(DATE(MID(B49,7,4),LEFT(B49,2),MID(B49,4,2))) -> 1
A50: ORD-49 | B50: 45570 | C50: West | D50: Alfie Edkins | E50: =IF(OR(K50="iPhone 15",K50="Samsung Galaxy"),"Mobiles",IF(OR(K50="HP Laptop",K50="Dell Laptop"),"Laptops","Accessories")) -> Mobiles | F50: 11 | G50: 11507 | H50: Pending | I50: =TEXT(DATE(MID(B50,7,4),LEFT(B50,2),MID(B50,4,2)),"MMM") -> May | J50: =if(H50="Returned",0,L50) -> 126577 | K50: iPhone 15 | L50: 126577 | M50: =MONTH(DATE(MID(B50,7,4),LEFT(B50,2),MID(B50,4,2))) -> 5
A51: ORD-50 | B51: 45515 | C51: East | D51: Percival Licciardi | E51: =IF(OR(K51="iPhone 15",K51="Samsung Galaxy"),"Mobiles",IF(OR(K51="HP Laptop",K51="Dell Laptop"),"Laptops","Accessories")) -> Mobiles | F51: 9 | G51: 76018 | H51: Completed | I51: =TEXT(DATE(MID(B51,7,4),LEFT(B51,2),MID(B51,4,2)),"MMM") -> Nov | J51: =if(H51="Returned",0,L51) -> 684162 | K51: iPhone 15 | L51: 684162 | M51: =MONTH(DATE(MID(B51,7,4),LEFT(B51,2),MID(B51,4,2))) -> 11
A52: ORD-51 | B52: 02/15/2024 | C52: West | D52: Tilda Warmisham | E52: =IF(OR(K52="iPhone 15",K52="Samsung Galaxy"),"Mobiles",IF(OR(K52="HP Laptop",K52="Dell Laptop"),"Laptops","Accessories")) -> Accessories | F52: 6 | G52: 62217 | H52: Completed | I52: =TEXT(DATE(MID(B52,7,4),LEFT(B52,2),MID(B52,4,2)),"MMM") -> Feb | J52: =if(H52="Returned",0,L52) -> 373302 | K52: Boat Earbuds | L52: 373302 | M52: =MONTH(DATE(MID(B52,7,4),LEFT(B52,2),MID(B52,4,2))) -> 2
A53: ORD-52 | B53: 10/23/2024 | C53: South | D53: Stewart Yanukhin | E53: =IF(OR(K53="iPhone 15",K53="Samsung Galaxy"),"Mobiles",IF(OR(K53="HP Laptop",K53="Dell Laptop"),"Laptops","Accessories")) -> Laptops | F53: 8 | G53: 50690 | H53: Completed | I53: =TEXT(DATE(MID(B53,7,4),LEFT(B53,2),MID(B53,4,2)),"MMM") -> Oct | J53: =if(H53="Returned",0,L53) -> 405520 | K53: HP Laptop | L53: 405520 | M53: =MONTH(DATE(MID(B53,7,4),LEFT(B53,2),MID(B53,4,2))) -> 10
A54: ORD-53 | B54: 45568 | C54: East | D54: Silvester Steiner | E54: =IF(OR(K54="iPhone 15",K54="Samsung Galaxy"),"Mobiles",IF(OR(K54="HP Laptop",K54="Dell Laptop"),"Laptops","Accessories")) -> Accessories | F54: 9 | G54: 38579 | H54: Completed | I54: =TEXT(DATE(MID(B54,7,4),LEFT(B54,2),MID(B54,4,2)),"MMM") -> Mar | J54: =if(H54="Returned",0,L54) -> 347211 | K54: OnePlus TV | L54: 347211 | M54: =MONTH(DATE(MID(B54,7,4),LEFT(B54,2),MID(B54,4,2))) -> 3
A55: ORD-54 | B55: 45638 | C55: South | D55: Calv Blackney | E55: =IF(OR(K55="iPhone 15",K55="Samsung Galaxy"),"Mobiles",IF(OR(K55="HP Laptop",K55="Dell Laptop"),"Laptops","Accessories")) -> Accessories | F55: 11 | G55: 77325 | H55: Pending | I55: =TEXT(DATE(MID(B55,7,4),LEFT(B55,2),MID(B55,4,2)),"MMM") -> Dec | J55: =if(H55="Returned",0,L55) -> 850575 | K55: Logitech Mouse | L55: 850575 | M55: =MONTH(DATE(MID(B55,7,4),LEFT(B55,2),MID(B55,4,2))) -> 12
A56: ORD-55 | B56: 08/23/2024 | C56: North | D56: Nicola Killcross | E56: =IF(OR(K56="iPhone 15",K56="Samsung Galaxy"),"Mobiles",IF(OR(K56="HP Laptop",K56="Dell Laptop"),"Laptops","Accessories")) -> Mobiles | F56: 13 | G56: 5631 | H56: Returned | I56: =TEXT(DATE(MID(B56,7,4),LEFT(B56,2),MID(B56,4,2)),"MMM") -> Aug | J56: =if(H56="Returned",0,L56) -> 0 | K56: iPhone 15 | L56: 73203 | M56: =MONTH(DATE(MID(B56,7,4),LEFT(B56,2),MID(B56,4,2))) -> 8
A57: ORD-56 | B57: 09/24/2024 | C57: North | D57: Denys Amberger | E57: =IF(OR(K57="iPhone 15",K57="Samsung Galaxy"),"Mobiles",IF(OR(K57="HP Laptop",K57="Dell Laptop"),"Laptops","Accessories")) -> Accessories | F57: 10 | G57: 783 | H57: Completed | I57: =TEXT(DATE(MID(B57,7,4),LEFT(B57,2),MID(B57,4,2)),"MMM") -> Sep | J57: =if(H57="Returned",0,L57) -> 7830 | K57: Boat Earbuds | L57: 7830 | M57: =MONTH(DATE(MID(B57,7,4),LEFT(B57,2),MID(B57,4,2))) -> 9
A58: ORD-57 | B58: 01/22/2024 | C58: East | D58: Vally Nyles | E58: =IF(OR(K58="iPhone 15",K58="Samsung Galaxy"),"Mobiles",IF(OR(K58="HP Laptop",K58="Dell Laptop"),"Laptops","Accessories")) -> Laptops | F58: 8 | G58: 32469 | H58: Completed | I58: =TEXT(DATE(MID(B58,7,4),LEFT(B58,2),MID(B58,4,2)),"MMM") -> Jan | J58: =if(H58="Returned",0,L58) -> 259752 | K58: Dell Laptop | L58: 259752 | M58: =MONTH(DATE(MID(B58,7,4),LEFT(B58,2),MID(B58,4,2))) -> 1
A59: ORD-58 | B59: 05/25/2024 | C59: West | D59: Pincas Nutten | E59: =IF(OR(K59="iPhone 15",K59="Samsung Galaxy"),"Mobiles",IF(OR(K59="HP Laptop",K59="Dell Laptop"),"Laptops","Accessories")) -> Accessories | F59: 13 | G59: 36675 | H59: Returned | I59: =TEXT(DATE(MID(B59,7,4),LEFT(B59,2),MID(B59,4,2)),"MMM") -> May | J59: =if(H59="Returned",0,L59) -> 0 | K59: Boat Earbuds | L59: 476775 | M59: =MONTH(DATE(MID(B59,7,4),LEFT(B59,2),MID(B59,4,2))) -> 5
A60: ORD-59 | B60: 02/20/2024 | C60: North | D60: Kit Sheards | E60: =IF(OR(K60="iPhone 15",K60="Samsung Galaxy"),"Mobiles",IF(OR(K60="HP Laptop",K60="Dell Laptop"),"Laptops","Accessories")) -> Mobiles | F60: 14 | G60: 1974 | H60: Returned | I60: =TEXT(DATE(MID(B60,7,4),LEFT(B60,2),MID(B60,4,2)),"MMM") -> Feb | J60: =if(H60="Returned",0,L60) -> 0 | K60: iPhone 15 | L60: 27636 | M60: =MONTH(DATE(MID(B60,7,4),LEFT(B60,2),MID(B60,4,2))) -> 2
A61: ORD-60 | B61: 45415 | C61: North | D61: Frans Lickorish | E61: =IF(OR(K61="iPhone 15",K61="Samsung Galaxy"),"Mobiles",IF(OR(K61="HP Laptop",K61="Dell Laptop"),"Laptops","Accessories")) -> Accessories | F61: 1 | G61: 58531 | H61: Pending | I61: =TEXT(DATE(MID(B61,7,4),LEFT(B61,2),MID(B61,4,2)),"MMM") -> Mar | J61: =if(H61="Returned",0,L61) -> 58531 | K61: Boat Earbuds | L61: 58531 | M61: =MONTH(DATE(MID(B61,7,4),LEFT(B61,2),MID(B61,4,2))) -> 3
A62: ORD-61 | B62: 45571 | C62: East | D62: Curcio Bondesen | E62: =IF(OR(K62="iPhone 15",K62="Samsung Galaxy"),"Mobiles",IF(OR(K62="HP Laptop",K62="Dell Laptop"),"Laptops","Accessories")) -> Accessories | F62: 3 | G62: 19588 | H62: Returned | I62: =TEXT(DATE(MID(B62,7,4),LEFT(B62,2),MID(B62,4,2)),"MMM") -> Jun | J62: =if(H62="Returned",0,L62) -> 0 | K62: Boat Earbuds | L62: 58764 | M62: =MONTH(DATE(MID(B62,7,4),LEFT(B62,2),MID(B62,4,2))) -> 6
A63: ORD-62 | B63: 06/14/2024 | C63: South | D63: Veronique Cajkler | E63: =IF(OR(K63="iPhone 15",K63="Samsung Galaxy"),"Mobiles",IF(OR(K63="HP Laptop",K63="Dell Laptop"),"Laptops","Accessories")) -> Mobiles | F63: 10 | G63: 56913 | H63: Returned | I63: =TEXT(DATE(MID(B63,7,4),LEFT(B63,2),MID(B63,4,2)),"MMM") -> Jun | J63: =if(H63="Returned",0,L63) -> 0 | K63: Samsung Galaxy | L63: 569130 | M63: =MONTH(DATE(MID(B63,7,4),LEFT(B63,2),MID(B63,4,2))) -> 6
A64: ORD-63 | B64: 45301 | C64: East | D64: Clare Frill | E64: =IF(OR(K64="iPhone 15",K64="Samsung Galaxy"),"Mobiles",IF(OR(K64="HP Laptop",K64="Dell Laptop"),"Laptops","Accessories")) -> Accessories | F64: 14 | G64: 38706 | H64: Pending | I64: =TEXT(DATE(MID(B64,7,4),LEFT(B64,2),MID(B64,4,2)),"MMM") -> Oct | J64: =if(H64="Returned",0,L64) -> 541884 | K64: Boat Earbuds | L64: 541884 | M64: =MONTH(DATE(MID(B64,7,4),LEFT(B64,2),MID(B64,4,2))) -> 10
A65: ORD-64 | B65: 45633 | C65: North | D65: Corrina German | E65: =IF(OR(K65="iPhone 15",K65="Samsung Galaxy"),"Mobiles",IF(OR(K65="HP Laptop",K65="Dell Laptop"),"Laptops","Accessories")) -> Accessories | F65: 9 | G65: 18791 | H65: Pending | I65: =TEXT(DATE(MID(B65,7,4),LEFT(B65,2),MID(B65,4,2)),"MMM") -> Jul | J65: =if(H65="Returned",0,L65) -> 169119 | K65: OnePlus TV | L65: 169119 | M65: =MONTH(DATE(MID(B65,7,4),LEFT(B65,2),MID(B65,4,2))) -> 7
A66: ORD-65 | B66: 12/20/2024 | C66: West | D66: Hendrika Ivashintsov | E66: =IF(OR(K66="iPhone 15",K66="Samsung Galaxy"),"Mobiles",IF(OR(K66="HP Laptop",K66="Dell Laptop"),"Laptops","Accessories")) -> Mobiles | F66: 2 | G66: 17982 | H66: Pending | I66: =TEXT(DATE(MID(B66,7,4),LEFT(B66,2),MID(B66,4,2)),"MMM") -> Dec | J66: =if(H66="Returned",0,L66) -> 35964 | K66: Samsung Galaxy | L66: 35964 | M66: =MONTH(DATE(MID(B66,7,4),LEFT(B66,2),MID(B66,4,2))) -> 12
A67: ORD-66 | B67: 45566 | C67: North | D67: Ewart Glasby | E67: =IF(OR(K67="iPhone 15",K67="Samsung Galaxy"),"Mobiles",IF(OR(K67="HP Laptop",K67="Dell Laptop"),"Laptops","Accessories")) -> Laptops | F67: 13 | G67: 34763 | H67: Returned | I67: =TEXT(DATE(MID(B67,7,4),LEFT(B67,2),MID(B67,4,2)),"MMM") -> Jan | J67: =if(H67="Returned",0,L67) -> 0 | K67: HP Laptop | L67: 451919 | M67: =MONTH(DATE(MID(B67,7,4),LEFT(B67,2),MID(B67,4,2))) -> 1
A68: ORD-67 | B68: 45444 | C68: South | D68: Balduin Mandifield | E68: =IF(OR(K68="iPhone 15",K68="Samsung Galaxy"),"Mobiles",IF(OR(K68="HP Laptop",K68="Dell Laptop"),"Laptops","Accessories")) -> Laptops | F68: 17 | G68: 52064 | H68: Pending | I68: =TEXT(DATE(MID(B68,7,4),LEFT(B68,2),MID(B68,4,2)),"MMM") -> Jan | J68: =if(H68="Returned",0,L68) -> 885088 | K68: HP Laptop | L68: 885088 | M68: =MONTH(DATE(MID(B68,7,4),LEFT(B68,2),MID(B68,4,2))) -> 1
A69: ORD-68 | B69: 11/27/2024 | C69: South | D69: Kevin Penney | E69: =IF(OR(K69="iPhone 15",K69="Samsung Galaxy"),"Mobiles",IF(OR(K69="HP Laptop",K69="Dell Laptop"),"Laptops","Accessories")) -> Mobiles | F69: 18 | G69: 37329 | H69: Pending | I69: =TEXT(DATE(MID(B69,7,4),LEFT(B69,2),MID(B69,4,2)),"MMM") -> Nov | J69: =if(H69="Returned",0,L69) -> 671922 | K69: iPhone 15 | L69: 671922 | M69: =MONTH(DATE(MID(B69,7,4),LEFT(B69,2),MID(B69,4,2))) -> 11
A70: ORD-69 | B70: 06/28/2024 | C70: West | D70: Arleyne Badham | E70: =IF(OR(K70="iPhone 15",K70="Samsung Galaxy"),"Mobiles",IF(OR(K70="HP Laptop",K70="Dell Laptop"),"Laptops","Accessories")) -> Laptops | F70: 1 | G70: 58945 | H70: Returned | I70: =TEXT(DATE(MID(B70,7,4),LEFT(B70,2),MID(B70,4,2)),"MMM") -> Jun | J70: =if(H70="Returned",0,L70) -> 0 | K70: Dell Laptop | L70: 58945 | M70: =MONTH(DATE(MID(B70,7,4),LEFT(B70,2),MID(B70,4,2))) -> 6
A71: ORD-70 | B71: 45332 | C71: North | D71: Ian Spary | E71: =IF(OR(K71="iPhone 15",K71="Samsung Galaxy"),"Mobiles",IF(OR(K71="HP Laptop",K71="Dell Laptop"),"Laptops","Accessories")) -> Mobiles | F71: 15 | G71: 30752 | H71: Returned | I71: =TEXT(DATE(MID(B71,7,4),LEFT(B71,2),MID(B71,4,2)),"MMM") -> Oct | J71: =if(H71="Returned",0,L71) -> 0 | K71: Samsung Galaxy | L71: 461280 | M71: =MONTH(DATE(MID(B71,7,4),LEFT(B71,2),MID(B71,4,2))) -> 10
A72: ORD-71 | B72: 05/30/2024 | C72: East | D72: Herc Chalmers | E72: =IF(OR(K72="iPhone 15",K72="Samsung Galaxy"),"Mobiles",IF(OR(K72="HP Laptop",K72="Dell Laptop"),"Laptops","Accessories")) -> Accessories | F72: 6 | G72: 20376 | H72: Returned | I72: =TEXT(DATE(MID(B72,7,4),LEFT(B72,2),MID(B72,4,2)),"MMM") -> May | J72: =if(H72="Returned",0,L72) -> 0 | K72: Logitech Mouse | L72: 122256 | M72: =MONTH(DATE(MID(B72,7,4),LEFT(B72,2),MID(B72,4,2))) -> 5
A73: ORD-72 | B73: 11/25/2024 | C73: West | D73: Saul Rhymer | E73: =IF(OR(K73="iPhone 15",K73="Samsung Galaxy"),"Mobiles",IF(OR(K73="HP Laptop",K73="Dell Laptop"),"Laptops","Accessories")) -> Accessories | F73: 12 | G73: 16751 | H73: Pending | I73: =TEXT(DATE(MID(B73,7,4),LEFT(B73,2),MID(B73,4,2)),"MMM") -> Nov | J73: =if(H73="Returned",0,L73) -> 201012 | K73: OnePlus TV | L73: 201012 | M73: =MONTH(DATE(MID(B73,7,4),LEFT(B73,2),MID(B73,4,2))) -> 11
A74: ORD-73 | B74: 45331 | C74: North | D74: Nicolais MacCrossan | E74: =IF(OR(K74="iPhone 15",K74="Samsung Galaxy"),"Mobiles",IF(OR(K74="HP Laptop",K74="Dell Laptop"),"Laptops","Accessories")) -> Laptops | F74: 8 | G74: 49186 | H74: Completed | I74: =TEXT(DATE(MID(B74,7,4),LEFT(B74,2),MID(B74,4,2)),"MMM") -> Sep | J74: =if(H74="Returned",0,L74) -> 393488 | K74: HP Laptop | L74: 393488 | M74: =MONTH(DATE(MID(B74,7,4),LEFT(B74,2),MID(B74,4,2))) -> 9
A75: ORD-74 | B75: 45482 | C75: South | D75: Osgood Claeskens | E75: =IF(OR(K75="iPhone 15",K75="Samsung Galaxy"),"Mobiles",IF(OR(K75="HP Laptop",K75="Dell Laptop"),"Laptops","Accessories")) -> Accessories | F75: 15 | G75: 24217 | H75: Pending | I75: =TEXT(DATE(MID(B75,7,4),LEFT(B75,2),MID(B75,4,2)),"MMM") -> Sep | J75: =if(H75="Returned",0,L75) -> 363255 | K75: Boat Earbuds | L75: 363255 | M75: =MONTH(DATE(MID(B75,7,4),LEFT(B75,2),MID(B75,4,2))) -> 9
A76: ORD-75 | B76: 45631 | C76: East | D76: Patrick Klimt | E76: =IF(OR(K76="iPhone 15",K76="Samsung Galaxy"),"Mobiles",IF(OR(K76="HP Laptop",K76="Dell Laptop"),"Laptops","Accessories")) -> Accessories | F76: 12 | G76: 30775 | H76: Completed | I76: =TEXT(DATE(MID(B76,7,4),LEFT(B76,2),MID(B76,4,2)),"MMM") -> May | J76: =if(H76="Returned",0,L76) -> 369300 | K76: Logitech Mouse | L76: 369300 | M76: =MONTH(DATE(MID(B76,7,4),LEFT(B76,2),MID(B76,4,2))) -> 5
A77: ORD-76 | B77: 45632 | C77: East | D77: Vic Hammond | E77: =IF(OR(K77="iPhone 15",K77="Samsung Galaxy"),"Mobiles",IF(OR(K77="HP Laptop",K77="Dell Laptop"),"Laptops","Accessories")) -> Mobiles | F77: 5 | G77: 6071 | H77: Pending | I77: =TEXT(DATE(MID(B77,7,4),LEFT(B77,2),MID(B77,4,2)),"MMM") -> Jun | J77: =if(H77="Returned",0,L77) -> 30355 | K77: iPhone 15 | L77: 30355 | M77: =MONTH(DATE(MID(B77,7,4),LEFT(B77,2),MID(B77,4,2))) -> 6
A78: ORD-77 | B78: 10/23/2024 | C78: West | D78: Barb Minihan | E78: =IF(OR(K78="iPhone 15",K78="Samsung Galaxy"),"Mobiles",IF(OR(K78="HP Laptop",K78="Dell Laptop"),"Laptops","Accessories")) -> Mobiles | F78: 20 | G78: 18627 | H78: Returned | I78: =TEXT(DATE(MID(B78,7,4),LEFT(B78,2),MID(B78,4,2)),"MMM") -> Oct | J78: =if(H78="Returned",0,L78) -> 0 | K78: iPhone 15 | L78: 372540 | M78: =MONTH(DATE(MID(B78,7,4),LEFT(B78,2),MID(B78,4,2))) -> 10
A79: ORD-78 | B79: 45568 | C79: East | D79: Curtis Ashburner | E79: =IF(OR(K79="iPhone 15",K79="Samsung Galaxy"),"Mobiles",IF(OR(K79="HP Laptop",K79="Dell Laptop"),"Laptops","Accessories")) -> Mobiles | F79: 9 | G79: 48389 | H79: Returned | I79: =TEXT(DATE(MID(B79,7,4),LEFT(B79,2),MID(B79,4,2)),"MMM") -> Mar | J79: =if(H79="Returned",0,L79) -> 0 | K79: Samsung Galaxy | L79: 435501 | M79: =MONTH(DATE(MID(B79,7,4),LEFT(B79,2),MID(B79,4,2))) -> 3
A80: ORD-79 | B80: 45638 | C80: East | D80: Emlyn Borrowman | E80: =IF(OR(K80="iPhone 15",K80="Samsung Galaxy"),"Mobiles",IF(OR(K80="HP Laptop",K80="Dell Laptop"),"Laptops","Accessories")) -> Accessories | F80: 7 | G80: 2916 | H80: Completed | I80: =TEXT(DATE(MID(B80,7,4),LEFT(B80,2),MID(B80,4,2)),"MMM") -> Dec | J80: =if(H80="Returned",0,L80) -> 20412 | K80: Boat Earbuds | L80: 20412 | M80: =MONTH(DATE(MID(B80,7,4),LEFT(B80,2),MID(B80,4,2))) -> 12
A81: ORD-80 | B81: 08/14/2024 | C81: East | D81: Vidovic Bonson | E81: =IF(OR(K81="iPhone 15",K81="Samsung Galaxy"),"Mobiles",IF(OR(K81="HP Laptop",K81="Dell Laptop"),"Laptops","Accessories")) -> Laptops | F81: 13 | G81: 79157 | H81: Pending | I81: =TEXT(DATE(MID(B81,7,4),LEFT(B81,2),MID(B81,4,2)),"MMM") -> Aug | J81: =if(H81="Returned",0,L81) -> 1029041 | K81: HP Laptop | L81: 1029041 | M81: =MONTH(DATE(MID(B81,7,4),LEFT(B81,2),MID(B81,4,2))) -> 8
A82: ORD-81 | B82: 45547 | C82: North | D82: Octavius Steggals | E82: =IF(OR(K82="iPhone 15",K82="Samsung Galaxy"),"Mobiles",IF(OR(K82="HP Laptop",K82="Dell Laptop"),"Laptops","Accessories")) -> Accessories | F82: 10 | G82: 62754 | H82: Pending | I82: =TEXT(DATE(MID(B82,7,4),LEFT(B82,2),MID(B82,4,2)),"MMM") -> Dec | J82: =if(H82="Returned",0,L82) -> 627540 | K82: Boat Earbuds | L82: 627540 | M82: =MONTH(DATE(MID(B82,7,4),LEFT(B82,2),MID(B82,4,2))) -> 12
A83: ORD-82 | B83: 45483 | C83: North | D83: Bobbee Hammerman | E83: =IF(OR(K83="iPhone 15",K83="Samsung Galaxy"),"Mobiles",IF(OR(K83="HP Laptop",K83="Dell Laptop"),"Laptops","Accessories")) -> Mobiles | F83: 16 | G83: 49327 | H83: Returned | I83: =TEXT(DATE(MID(B83,7,4),LEFT(B83,2),MID(B83,4,2)),"MMM") -> Oct | J83: =if(H83="Returned",0,L83) -> 0 | K83: iPhone 15 | L83: 789232 | M83: =MONTH(DATE(MID(B83,7,4),LEFT(B83,2),MID(B83,4,2))) -> 10
A84: ORD-83 | B84: 10/29/2024 | C84: North | D84: Mercie Lines | E84: =IF(OR(K84="iPhone 15",K84="Samsung Galaxy"),"Mobiles",IF(OR(K84="HP Laptop",K84="Dell Laptop"),"Laptops","Accessories")) -> Laptops | F84: 7 | G84: 60535 | H84: Completed | I84: =TEXT(DATE(MID(B84,7,4),LEFT(B84,2),MID(B84,4,2)),"MMM") -> Oct | J84: =if(H84="Returned",0,L84) -> 423745 | K84: Dell Laptop | L84: 423745 | M84: =MONTH(DATE(MID(B84,7,4),LEFT(B84,2),MID(B84,4,2))) -> 10
A85: ORD-84 | B85: 45384 | C85: West | D85: Giovanni Gostyke | E85: =IF(OR(K85="iPhone 15",K85="Samsung Galaxy"),"Mobiles",IF(OR(K85="HP Laptop",K85="Dell Laptop"),"Laptops","Accessories")) -> Mobiles | F85: 12 | G85: 66313 | H85: Pending | I85: =TEXT(DATE(MID(B85,7,4),LEFT(B85,2),MID(B85,4,2)),"MMM") -> Feb | J85: =if(H85="Returned",0,L85) -> 795756 | K85: iPhone 15 | L85: 795756 | M85: =MONTH(DATE(MID(B85,7,4),LEFT(B85,2),MID(B85,4,2))) -> 2
A86: ORD-85 | B86: 05/20/2024 | C86: East | D86: Gabbey Christopher | E86: =IF(OR(K86="iPhone 15",K86="Samsung Galaxy"),"Mobiles",IF(OR(K86="HP Laptop",K86="Dell Laptop"),"Laptops","Accessories")) -> Mobiles | F86: 5 | G86: 75146 | H86: Completed | I86: =TEXT(DATE(MID(B86,7,4),LEFT(B86,2),MID(B86,4,2)),"MMM") -> May | J86: =if(H86="Returned",0,L86) -> 375730 | K86: iPhone 15 | L86: 375730 | M86: =MONTH(DATE(MID(B86,7,4),LEFT(B86,2),MID(B86,4,2))) -> 5
A87: ORD-86 | B87: 09/13/2024 | C87: North | D87: Kendricks Keneforde | E87: =IF(OR(K87="iPhone 15",K87="Samsung Galaxy"),"Mobiles",IF(OR(K87="HP Laptop",K87="Dell Laptop"),"Laptops","Accessories")) -> Accessories | F87: 11 | G87: 24127 | H87: Completed | I87: =TEXT(DATE(MID(B87,7,4),LEFT(B87,2),MID(B87,4,2)),"MMM") -> Sep | J87: =if(H87="Returned",0,L87) -> 265397 | K87: Logitech Mouse | L87: 265397 | M87: =MONTH(DATE(MID(B87,7,4),LEFT(B87,2),MID(B87,4,2))) -> 9
A88: ORD-87 | B88: 03/24/2024 | C88: East | D88: Trumaine Molloy | E88: =IF(OR(K88="iPhone 15",K88="Samsung Galaxy"),"Mobiles",IF(OR(K88="HP Laptop",K88="Dell Laptop"),"Laptops","Accessories")) -> Accessories | F88: 5 | G88: 70416 | H88: Completed | I88: =TEXT(DATE(MID(B88,7,4),LEFT(B88,2),MID(B88,4,2)),"MMM") -> Mar | J88: =if(H88="Returned",0,L88) -> 352080 | K88: Logitech Mouse | L88: 352080 | M88: =MONTH(DATE(MID(B88,7,4),LEFT(B88,2),MID(B88,4,2))) -> 3
A89: ORD-88 | B89: 05/24/2024 | C89: East | D89: Brunhilde Jerke | E89: =IF(OR(K89="iPhone 15",K89="Samsung Galaxy"),"Mobiles",IF(OR(K89="HP Laptop",K89="Dell Laptop"),"Laptops","Accessories")) -> Accessories | F89: 8 | G89: 18452 | H89: Pending | I89: =TEXT(DATE(MID(B89,7,4),LEFT(B89,2),MID(B89,4,2)),"MMM") -> May | J89: =if(H89="Returned",0,L89) -> 147616 | K89: Logitech Mouse | L89: 147616 | M89: =MONTH(DATE(MID(B89,7,4),LEFT(B89,2),MID(B89,4,2))) -> 5
A90: ORD-89 | B90: 45448 | C90: North | D90: Lamont Rosenstengel | E90: =IF(OR(K90="iPhone 15",K90="Samsung Galaxy"),"Mobiles",IF(OR(K90="HP Laptop",K90="Dell Laptop"),"Laptops","Accessories")) -> Accessories | F90: 19 | G90: 6820 | H90: Completed | I90: =TEXT(DATE(MID(B90,7,4),LEFT(B90,2),MID(B90,4,2)),"MMM") -> May | J90: =if(H90="Returned",0,L90) -> 129580 | K90: Boat Earbuds | L90: 129580 | M90: =MONTH(DATE(MID(B90,7,4),LEFT(B90,2),MID(B90,4,2))) -> 5
A91: ORD-90 | B91: 11/29/2024 | C91: East | D91: Silvana McKirton | E91: =IF(OR(K91="iPhone 15",K91="Samsung Galaxy"),"Mobiles",IF(OR(K91="HP Laptop",K91="Dell Laptop"),"Laptops","Accessories")) -> Laptops | F91: 10 | G91: 10098 | H91: Returned | I91: =TEXT(DATE(MID(B91,7,4),LEFT(B91,2),MID(B91,4,2)),"MMM") -> Nov | J91: =if(H91="Returned",0,L91) -> 0 | K91: Dell Laptop | L91: 100980 | M91: =MONTH(DATE(MID(B91,7,4),LEFT(B91,2),MID(B91,4,2))) -> 11
A92: ORD-91 | B92: 11/24/2024 | C92: South | D92: Chip Cathery | E92: =IF(OR(K92="iPhone 15",K92="Samsung Galaxy"),"Mobiles",IF(OR(K92="HP Laptop",K92="Dell Laptop"),"Laptops","Accessories")) -> Mobiles | F92: 2 | G92: 18221 | H92: Pending | I92: =TEXT(DATE(MID(B92,7,4),LEFT(B92,2),MID(B92,4,2)),"MMM") -> Nov | J92: =if(H92="Returned",0,L92) -> 36442 | K92: Samsung Galaxy | L92: 36442 | M92: =MONTH(DATE(MID(B92,7,4),LEFT(B92,2),MID(B92,4,2))) -> 11
A93: ORD-92 | B93: 09/16/2024 | C93: North | D93: Anselm Oldacres | E93: =IF(OR(K93="iPhone 15",K93="Samsung Galaxy"),"Mobiles",IF(OR(K93="HP Laptop",K93="Dell Laptop"),"Laptops","Accessories")) -> Laptops | F93: 13 | G93: 42310 | H93: Returned | I93: =TEXT(DATE(MID(B93,7,4),LEFT(B93,2),MID(B93,4,2)),"MMM") -> Sep | J93: =if(H93="Returned",0,L93) -> 0 | K93: HP Laptop | L93: 550030 | M93: =MONTH(DATE(MID(B93,7,4),LEFT(B93,2),MID(B93,4,2))) -> 9
A94: ORD-93 | B94: 45630 | C94: East | D94: Robby Burnyeat | E94: =IF(OR(K94="iPhone 15",K94="Samsung Galaxy"),"Mobiles",IF(OR(K94="HP Laptop",K94="Dell Laptop"),"Laptops","Accessories")) -> Accessories | F94: 13 | G94: 46844 | H94: Returned | I94: =TEXT(DATE(MID(B94,7,4),LEFT(B94,2),MID(B94,4,2)),"MMM") -> Apr | J94: =if(H94="Returned",0,L94) -> 0 | K94: Logitech Mouse | L94: 608972 | M94: =MONTH(DATE(MID(B94,7,4),LEFT(B94,2),MID(B94,4,2))) -> 4
A95: ORD-94 | B95: 01/29/2024 | C95: West | D95: Gannie Pruckner | E95: =IF(OR(K95="iPhone 15",K95="Samsung Galaxy"),"Mobiles",IF(OR(K95="HP Laptop",K95="Dell Laptop"),"Laptops","Accessories")) -> Accessories | F95: 5 | G95: 60595 | H95: Pending | I95: =TEXT(DATE(MID(B95,7,4),LEFT(B95,2),MID(B95,4,2)),"MMM") -> Jan | J95: =if(H95="Returned",0,L95) -> 302975 | K95: Boat Earbuds | L95: 302975 | M95: =MONTH(DATE(MID(B95,7,4),LEFT(B95,2),MID(B95,4,2))) -> 1
A96: ORD-95 | B96: 45540 | C96: East | D96: Essie Nossent | E96: =IF(OR(K96="iPhone 15",K96="Samsung Galaxy"),"Mobiles",IF(OR(K96="HP Laptop",K96="Dell Laptop"),"Laptops","Accessories")) -> Laptops | F96: 9 | G96: 25211 | H96: Completed | I96: =TEXT(DATE(MID(B96,7,4),LEFT(B96,2),MID(B96,4,2)),"MMM") -> May | J96: =if(H96="Returned",0,L96) -> 226899 | K96: Dell Laptop | L96: 226899 | M96: =MONTH(DATE(MID(B96,7,4),LEFT(B96,2),MID(B96,4,2))) -> 5
A97: ORD-96 | B97: 08/15/2024 | C97: South | D97: Fanny Smalman | E97: =IF(OR(K97="iPhone 15",K97="Samsung Galaxy"),"Mobiles",IF(OR(K97="HP Laptop",K97="Dell Laptop"),"Laptops","Accessories")) -> Accessories | F97: 7 | G97: 52954 | H97: Pending | I97: =TEXT(DATE(MID(B97,7,4),LEFT(B97,2),MID(B97,4,2)),"MMM") -> Aug | J97: =if(H97="Returned",0,L97) -> 370678 | K97: Logitech Mouse | L97: 370678 | M97: =MONTH(DATE(MID(B97,7,4),LEFT(B97,2),MID(B97,4,2))) -> 8
A98: ORD-97 | B98: 45636 | C98: North | D98: Deeann Annets | E98: =IF(OR(K98="iPhone 15",K98="Samsung Galaxy"),"Mobiles",IF(OR(K98="HP Laptop",K98="Dell Laptop"),"Laptops","Accessories")) -> Accessories | F98: 13 | G98: 1453 | H98: Completed | I98: =TEXT(DATE(MID(B98,7,4),LEFT(B98,2),MID(B98,4,2)),"MMM") -> Oct | J98: =if(H98="Returned",0,L98) -> 18889 | K98: OnePlus TV | L98: 18889 | M98: =MONTH(DATE(MID(B98,7,4),LEFT(B98,2),MID(B98,4,2))) -> 10
A99: ORD-98 | B99: 07/23/2024 | C99: West | D99: Kristi Hoodless | E99: =IF(OR(K99="iPhone 15",K99="Samsung Galaxy"),"Mobiles",IF(OR(K99="HP Laptop",K99="Dell Laptop"),"Laptops","Accessories")) -> Mobiles | F99: 7 | G99: 49538 | H99: Pending | I99: =TEXT(DATE(MID(B99,7,4),LEFT(B99,2),MID(B99,4,2)),"MMM") -> Jul | J99: =if(H99="Returned",0,L99) -> 346766 | K99: iPhone 15 | L99: 346766 | M99: =MONTH(DATE(MID(B99,7,4),LEFT(B99,2),MID(B99,4,2))) -> 7
A100: ORD-99 | B100: 45628 | C100: East | D100: Bil Ivanchov | E100: =IF(OR(K100="iPhone 15",K100="Samsung Galaxy"),"Mobiles",IF(OR(K100="HP Laptop",K100="Dell Laptop"),"Laptops","Accessories")) -> Laptops | F100: 7 | G100: 65875 | H100: Completed | I100: =TEXT(DATE(MID(B100,7,4),LEFT(B100,2),MID(B100,4,2)),"MMM") -> Feb | J100: =if(H100="Returned",0,L100) -> 461125 | K100: Dell Laptop | L100: 461125 | M100: =MONTH(DATE(MID(B100,7,4),LEFT(B100,2),MID(B100,4,2))) -> 2
...

Sheet Analysis
A1: Total revenue for the year | B1: =sum(Sales!J2:J301) -> 88015803
A3: Revenue broken down by each region | B3: North | C3: =SUMIF(Sales!C:C,"north",Sales!J:J) -> 17765314
B4: East | C4: =SUMIF(Sales!C:C,"east",Sales!J:J) -> 23604410
B5: West | C5: =SUMIF(Sales!C:C,"west",Sales!J:J) -> 20271674
B6: South | C6: =SUMIF(Sales!C:C,"south",Sales!J:J) -> 26374405
A8: Best performing salesperson | B8: {=INDEX(Sales!D:D,MATCH(MAX(Sales!J:J),Sales!J:J,0))} -> Britney Siddaley
A10: No. of orders returned | B10: =COUNTIF(Sales!H:H,"returned") -> 88
A12: highest sales month | B12: Dec
A14: average order value per category | B14: Mobiles | C14: =AVERAGEIF(Sales!E:E,"mobiles",Sales!J:J) -> 294196.69
B15: Accessories | C15: =AVERAGEIF(Sales!E:E,"accessories",Sales!J:J) -> 257216.39
B16: Laptops | C16: =AVERAGEIF(Sales!E:E,"laptops",Sales!J:J) -> 357815.19
A18: Top Product by Revenue | B18: {=INDEX(Sales!K:K,MATCH(MAX(SUMIF(Sales!K:K,Sales!K:K,Sales!J:J)),SUMIF(Sales!K:K,Sales!K:K,Sales!J:J),0))} -> iPhone 15
A20: Salesperson with Most Orders | B20: =Analysis!B8 -> Britney Siddaley
A22: Completion Rate by Region | B22: North | C22: =(COUNTIFS(Sales!C:C,"north",Sales!H:H,"completed")/COUNTIF(Sales!C:C,"north")*100) -> 33.333333
B23: East | C23: =(COUNTIFS(Sales!C:C,"east",Sales!H:H,"completed")/COUNTIF(Sales!C:C,"east")*100) -> 32.5
B24: West | C24: =COUNTIFS(Sales!C:C,"West",Sales!H:H,"Completed")/COUNTIF(Sales!C:C,"West")*100 -> 31.944444
B25: South | C25: =(COUNTIFS(Sales!C:C,"south",Sales!H:H,"completed")/COUNTIF(Sales!C:C,"south")*100) -> 27.848101
A27: Most Common Product Sold | B27: {=INDEX(Sales!K:K,MATCH(MAX(COUNTIF(Sales!K:K,Sales!K:K)),COUNTIF(Sales!K:K,Sales!K:K),0))} -> iPhone 15

Sheet Region_Month

Sheet Salesperson

Sheet Category

Sheet Order_Status

Sheet Total_category_Revenue

Sheet Dashboard
A12: Total Revenue | B12: Total Orders | C12: Best Salesperson | D12: Return Rate
A13: =SUM(Sales!J:J) -> 88015803 | B13: 300 | C13: =Analysis!B8 -> Britney Siddaley | D13: 0.29
